pb_speak/__init__.py
pb_speak/pb_speak.py
pb_speak-1.0.2.dist-info/LICENSE
pb_speak-1.0.2.dist-info/METADATA
pb_speak-1.0.2.dist-info/WHEEL
pb_speak-1.0.2.dist-info/top_level.txt
pb_speak-1.0.2.dist-info/RECORD
