Metadata-Version: 2.1
Name: pb-speak
Version: 1.0.2
Summary: A customizable text-to-speech Python library
Home-page: https://github.com/FalconX80/pb_speak
Author: Priyanshu Bhatt
Author-email: priyanshubhatt80@gmail.com
License: MIT
Classifier: Programming Language :: Python :: 3
Classifier: License :: OSI Approved :: MIT License
Classifier: Operating System :: OS Independent
Requires-Python: >=3.6
License-File: LICENSE
Requires-Dist: pyttsx3
